allure_commons_test/__init__.py
allure_commons_test/container.py
allure_commons_test/content.py
allure_commons_test/label.py
allure_commons_test/lookup.py
allure_commons_test/report.py
allure_commons_test/result.py
allure_python_commons_test-2.15.3.dist-info/METADATA
allure_python_commons_test-2.15.3.dist-info/WHEEL
allure_python_commons_test-2.15.3.dist-info/top_level.txt
allure_python_commons_test-2.15.3.dist-info/RECORD
