Metadata-Version: 2.4
Name: allure-python-commons-test
Version: 2.15.3
Summary: A collection of PyHamcrest matchers to test Allure adapters for Python test frameworks
Home-page: https://allurereport.org/
Author: Qameta Software Inc., Stanislav Seliverstov
Author-email: sseliverstov@qameta.io
License: Apache-2.0
Project-URL: Source, https://github.com/allure-framework/allure-python
Keywords: allure reporting testing matchers
Classifier: Development Status :: 5 - Production/Stable
Classifier: Intended Audience :: Developers
Classifier: License :: OSI Approved :: Apache Software License
Classifier: Topic :: Software Development :: Quality Assurance
Classifier: Topic :: Software Development :: Testing
Classifier: Programming Language :: Python :: 3
Classifier: Programming Language :: Python :: 3 :: Only
Classifier: Programming Language :: Python :: 3.8
Classifier: Programming Language :: Python :: 3.9
Classifier: Programming Language :: Python :: 3.10
Classifier: Programming Language :: Python :: 3.11
Classifier: Programming Language :: Python :: 3.12
Classifier: Programming Language :: Python :: 3.13
Requires-Dist: pyhamcrest>=1.9.0
Dynamic: author
Dynamic: author-email
Dynamic: classifier
Dynamic: description
Dynamic: description-content-type
Dynamic: home-page
Dynamic: keywords
Dynamic: license
Dynamic: project-url
Dynamic: requires-dist
Dynamic: summary
